{
    "adam" : {
        "name" : "Adam Drummond",
        "hackathons" : [
            {
                "name" : "Hack and Wellness",
                "prize" : "Best domain from Domain.com"
            },
            {
                "name" : "CorgiHacks",
                "prize" : "Best domain from GoDaddy"
            }
        ]
    }
    "jenna" : {
        "name" : "Jenna Everard",
        "hackathons" : [
            {
                "name" : "Own the Internet Hackathon",
                "prize" : "Finalist & Judges Choice Award"
            },
            {
                "name" : "Columbia DivHacks",
                "prize" : "Pinterest Anti-Racism Hack Honorable Mention"
            },
            {
                "name" : "CorgiHacks",
                "prize" : "Third Overall & Best Use of Linode"
            }
        ]
    }
}
